comgen/__init__.py
comgen/constraint_system/__init__.py
comgen/constraint_system/common.py
comgen/constraint_system/composition.py
comgen/constraint_system/distance.py
comgen/constraint_system/nn.py
comgen/constraint_system/synthesis.py
comgen/query/__init__.py
comgen/query/base.py
comgen/query/common.py
comgen/query/ionic.py
comgen/util/__init__.py
comgen/util/data.py
comgen/util/species.py
comgen/util/verify.py
comgen/util/data_files/__init__.py
comgen/util/data_files/common_poly_ions.txt
comgen/util/data_files/periodic_table.json
comgen/util/data_files/pettifor.json
comgen-0.0.21.dist-info/METADATA
comgen-0.0.21.dist-info/WHEEL
comgen-0.0.21.dist-info/top_level.txt
comgen-0.0.21.dist-info/RECORD
